pure_magic_rs/__init__.py
pure_magic_rs/__init__.pyi
pure_magic_rs/pure_magic_rs.pypy311-pp73-x86_64-linux-gnu.so
pure_magic_rs/py.typed
pure_magic_rs-0.3.1.dist-info/METADATA
pure_magic_rs-0.3.1.dist-info/WHEEL
pure_magic_rs-0.3.1.dist-info/RECORD
