Metadata-Version: 2.4
Name: pure-magic-rs
Version: 0.3.1
Classifier: Programming Language :: Rust
Classifier: Programming Language :: Python :: Implementation :: CPython
Classifier: Programming Language :: Python :: Implementation :: PyPy
Summary: Python bindings for pure-magic crate, a pure Rust re-implementation of libmagic
Keywords: magic,file,mime,identification,libmagic
Author-email: Quentin JEROME <quentin.jerome@circl.lu>
Maintainer-email: Quentin JEROME <quentin.jerome@circl.lu>
Requires-Python: >=3.8
Project-URL: Issues, https://github.com/qjerome/magic-rs/issues
Project-URL: Repository, https://github.com/qjerome/magic-rs
